CHANGELOG.rst
MANIFEST.in
license.txt
readme.rst
setup.cfg
setup.py
dbversioning/__init__.py
dbversioning/dbvctrl.py
dbversioning/dbvctrlConst.py
dbversioning/errorUtil.py
dbversioning/osUtil.py
dbversioning/repositoryconf.py
dbversioning/versionedDb.py
dbversioning/versionedDbConnection.py
dbversioning/versionedDbHelper.py
dbversioning/versionedDbShellUtil.py
dbversioning/versionedDbUtil.py
pgvctrl.egg-info/PKG-INFO
pgvctrl.egg-info/SOURCES.txt
pgvctrl.egg-info/dependency_links.txt
pgvctrl.egg-info/entry_points.txt
pgvctrl.egg-info/requires.txt
pgvctrl.egg-info/top_level.txt
test/test_util.py
test/config/__init__.py
test/config/test_basic_config_functions.py
test/config/test_conf.py
test/config/test_config_updating.py
test/db_shell_util/__init__.py
test/db_shell_util/test_db_shell_util.py
test/initialize_database/__init__.py
test/initialize_database/test_init_db.py
test/initialize_database/test_init_table_owner.py
test/initialize_database/test_init_without_db.py
test/non_produciton_db/__init__.py
test/non_produciton_db/test_basic_operations.py
test/non_produciton_db/test_dump_database.py
test/non_produciton_db/test_dump_database_list.py
test/non_produciton_db/test_env.py
test/non_produciton_db/test_pull_data.py
test/non_produciton_db/test_push_data.py
test/non_produciton_db/test_restore_database.py
test/non_produciton_db/test_schema_snapshot.py
test/non_produciton_db/test_schema_snapshot_list.py
test/non_produciton_db/test_status_check.py
test/non_produciton_db/test_time_feature.py
test/params_groups/__init__.py
test/params_groups/test_connection_list.py
test/params_groups/test_params_groups.py
test/prodcution_db/__init__.py
test/prodcution_db/test_basic_operations.py
test/prodcution_db/test_env.py
test/prodcution_db/test_push.py
test/repository/__init__.py
test/repository/test_make_remove.py
test/repository/test_repo_list.py
test/repository/test_repo_make_version.py
test/repository/test_repo_remove_version.py