Metadata-Version: 2.1
Name: pgvctrl
Version: 1.2.0
Summary: postgreSQL database version control tool
Home-page: https://github.com/87thstdev/pgvctrl
Author: Heath Sutton
Author-email: 87thstreetdevelopment@gmail.com
License: MIT
Keywords: postgres version control sql migrate migration patch patches
Platform: UNKNOWN
Requires-Python: >=3.6
